trac/__init__.py
trac/about.py
trac/api.py
trac/attachment.py
trac/cache.py
trac/config.py
trac/core.py
trac/db_default.py
trac/dist.py
trac/env.py
trac/loader.py
trac/log.py
trac/perm.py
trac/resource.py
trac/test.py
trac/admin/__init__.py
trac/admin/api.py
trac/admin/console.py
trac/admin/test.py
trac/admin/web_ui.py
trac/admin/templates/admin.html
trac/admin/templates/admin_basics.html
trac/admin/templates/admin_logging.html
trac/admin/templates/admin_perms.html
trac/admin/templates/admin_plugins.html
trac/db/__init__.py
trac/db/api.py
trac/db/convert.py
trac/db/mysql_backend.py
trac/db/pool.py
trac/db/postgres_backend.py
trac/db/schema.py
trac/db/sqlite_backend.py
trac/db/util.py
trac/htdocs/README
trac/htdocs/asc.png
trac/htdocs/attachment.png
trac/htdocs/batchmodify.png
trac/htdocs/changeset.png
trac/htdocs/closedticket.png
trac/htdocs/collapsed.png
trac/htdocs/desc.png
trac/htdocs/dots.gif
trac/htdocs/download.png
trac/htdocs/draft.png
trac/htdocs/edit_toolbar.png
trac/htdocs/editedticket.png
trac/htdocs/envelope.png
trac/htdocs/expanded.png
trac/htdocs/expander_normal.png
trac/htdocs/expander_normal_hover.png
trac/htdocs/expander_open.png
trac/htdocs/expander_open_hover.png
trac/htdocs/extlink.gif
trac/htdocs/feed.png
trac/htdocs/file.png
trac/htdocs/folder.png
trac/htdocs/grip.png
trac/htdocs/ics.png
trac/htdocs/imggrid.png
trac/htdocs/inreply.png
trac/htdocs/loading.gif
trac/htdocs/lock-locked.png
trac/htdocs/milestone.png
trac/htdocs/newticket.png
trac/htdocs/parent.png
trac/htdocs/python.png
trac/htdocs/topbar_gradient.png
trac/htdocs/topbar_gradient2.png
trac/htdocs/trac.ico
trac/htdocs/trac_banner.png
trac/htdocs/trac_logo_mini.png
trac/htdocs/vgradient.png
trac/htdocs/wiki.png
trac/htdocs/css/admin.css
trac/htdocs/css/browser.css
trac/htdocs/css/changeset.css
trac/htdocs/css/code.css
trac/htdocs/css/diff.css
trac/htdocs/css/jquery-ui-addons.css
trac/htdocs/css/prefs.css
trac/htdocs/css/report.css
trac/htdocs/css/roadmap.css
trac/htdocs/css/search.css
Trac-1.6.dist-info/AUTHORS
Trac-1.6.dist-info/COPYING
Trac-1.6.dist-info/METADATA
Trac-1.6.dist-info/WHEEL
Trac-1.6.dist-info/entry_points.txt
Trac-1.6.dist-info/top_level.txt
Trac-1.6.dist-info/zip-safe
Trac-1.6.dist-info/RECORD
