Metadata-Version: 2.1
Name: Trac
Version: 1.6
Summary: Integrated SCM, wiki, issue tracker and project environment
Home-page: https://trac.edgewall.org
Download-URL: https://trac.edgewall.org/wiki/TracDownload
Author: Edgewall Software
Author-email: trac-dev@googlegroups.com
License: BSD
Classifier: Environment :: Web Environment
Classifier: Framework :: Trac
Classifier: Intended Audience :: Developers
Classifier: License :: OSI Approved :: BSD License
Classifier: Operating System :: OS Independent
Classifier: Programming Language :: Python
Classifier: Programming Language :: Python :: 3
Classifier: Programming Language :: Python :: 3.5
Classifier: Programming Language :: Python :: 3.6
Classifier: Programming Language :: Python :: 3.7
Classifier: Programming Language :: Python :: 3.8
Classifier: Programming Language :: Python :: 3.9
Classifier: Programming Language :: Python :: 3.10
Classifier: Programming Language :: Python :: 3.11
Classifier: Topic :: Software Development :: Bug Tracking
Classifier: Topic :: Software Development :: Version Control
Requires-Python: >=3.5
License-File: COPYING
License-File: AUTHORS
Requires-Dist: setuptools>=30.3
Requires-Dist: jinja2>=2.9.3
Requires-Dist: multipart; python_version >= "3.13"
Provides-Extra: babel
Requires-Dist: Babel<2.10,>=2.2; extra == "babel"
Provides-Extra: mysql
Requires-Dist: PyMySQL; extra == "mysql"
Provides-Extra: postgresql
Requires-Dist: psycopg2>=2.5; extra == "postgresql"
Provides-Extra: psycopg2
Requires-Dist: psycopg2>=2.5; extra == "psycopg2"
Provides-Extra: psycopg2-binary
Requires-Dist: psycopg2-binary; extra == "psycopg2-binary"
Provides-Extra: pygments
Requires-Dist: Pygments>=1.0; extra == "pygments"
Provides-Extra: rest
Requires-Dist: docutils>=0.14; extra == "rest"
Provides-Extra: textile
Requires-Dist: textile>=2.3; extra == "textile"
